angr_management-9.2.193.dist-info/licenses/LICENSE
angrmanagement/__init__.py
angrmanagement/__main__.py
angrmanagement/consts.py
angrmanagement/errors.py
angrmanagement/config/__init__.py
angrmanagement/config/color_schemes.py
angrmanagement/config/config_entry.py
angrmanagement/config/config_manager.py
angrmanagement/daemon/__init__.py
angrmanagement/daemon/client.py
angrmanagement/daemon/server.py
angrmanagement/daemon/url_handler.py
angrmanagement/data/__init__.py
angrmanagement/data/analysis_options.py
angrmanagement/data/breakpoint.py
angrmanagement/data/function_graph.py
angrmanagement/data/highlight_region.py
angrmanagement/data/instance.py
angrmanagement/data/library_docs.py
angrmanagement/data/log.py
angrmanagement/data/object_container.py
angrmanagement/data/signatures.py
angrmanagement/data/tagged_interval_map.py
angrmanagement/data/trace.py
angrmanagement/data/jobs/__init__.py
angrmanagement/data/jobs/bindiff_matching.py
angrmanagement/data/jobs/calling_convention_recovery.py
angrmanagement/data/jobs/cfg_generation.py
angrmanagement/data/jobs/code_tagging.py
angrmanagement/data/jobs/ddg_generation.py
angrmanagement/data/jobs/decompile_function.py
angrmanagement/data/jobs/deobfuscation.py
angrmanagement/data/jobs/dependency_analysis.py
angrmanagement/data/jobs/flirt_signature_recognition.py
angrmanagement/data/jobs/job.py
angrmanagement/data/jobs/loading.py
angrmanagement/data/jobs/prototype_finding.py
angrmanagement/data/jobs/simgr_explore.py
angrmanagement/data/jobs/simgr_step.py
angrmanagement/data/jobs/variable_recovery.py
angrmanagement/data/jobs/vfg_generation.py
angrmanagement/logic/__init__.py
angrmanagement/logic/analysis_manager.py
angrmanagement/logic/jobmanager.py
angrmanagement/logic/singleton.py
angrmanagement/logic/threads.py
angrmanagement/logic/url_scheme.py
angrmanagement/logic/commands/__init__.py
angrmanagement/logic/commands/command.py
angrmanagement/logic/commands/command_manager.py
angrmanagement/logic/debugger/__init__.py
angrmanagement/logic/debugger/bintrace.py
angr_management-9.2.193.dist-info/METADATA
angr_management-9.2.193.dist-info/WHEEL
angr_management-9.2.193.dist-info/entry_points.txt
angr_management-9.2.193.dist-info/top_level.txt
angr_management-9.2.193.dist-info/RECORD
